ts_hyperparam_opt/__init__.py
ts_hyperparam_opt/parallel_hyperparameter_optimization.py
ts_hyperparam_opt-0.1.3.dist-info/LICENSE
ts_hyperparam_opt-0.1.3.dist-info/METADATA
ts_hyperparam_opt-0.1.3.dist-info/WHEEL
ts_hyperparam_opt-0.1.3.dist-info/top_level.txt
ts_hyperparam_opt-0.1.3.dist-info/RECORD
