Metadata-Version: 2.1
Name: ts-hyperparam-opt
Version: 0.1.3
Summary: Convenience package for parallelized hyperparameter optimization (e.g. in Jupyter Notebooks) using grid search and CV
Author: nick2202
License: MIT License
Project-URL: Homepage, https://github.com/nick2202/ts-hyperparam-opt
Project-URL: Bug Tracker, https://github.com/nick2202/ts-hyperparam-opt/issues
Keywords: python,time series,hyperparameter optimization,cross validation,parallel
Classifier: Programming Language :: Python :: 3
Classifier: License :: OSI Approved :: MIT License
Classifier: Operating System :: OS Independent
Requires-Python: >=3.8
License-File: LICENSE
Requires-Dist: numpy
Requires-Dist: statsmodels
Requires-Dist: scikit-learn
